{"stats":{"minecraft:crafted":{"afeibailismod:cerulean_planks":8,"afeibailismod:cerulean_axe":1,"afeibailismod:cerulean_sword":1,"afeibailismod:cerulean_pickaxe":1,"afeibailismod:cerulean_shove":1},"minecraft:picked_up":{"afeibailismod:smelly_cat":5,"minecraft:crafting_table":2,"afeibailismod:cerulean_planks":1,"afeibailismod:cerulean_hoe":1,"afeibailismod:qingyun_sharp_pickaxe":2,"afeibailismod:shadowed_shovel_blade":1,"minecraft:dirt":16,"afeibailismod:cerulean_log":3,"minecraft:item_frame":3,"afeibailismod:sapphire":2,"minecraft:cobbled_deepslate":1,"afeibailismod:inferno_dragon":1,"afeibailismod:cerulean_sword":1,"afeibailismod:ruby":2},"minecraft:used":{"afeibailismod:shadowed_shovel_blade":3,"minecraft:item_frame":3,"afeibailismod:cerulean_pickaxe":3,"afeibailismod:qingyun_sharp_pickaxe":2,"minecraft:dirt":16,"afeibailismod:cerulean_planks":1,"minecraft:crafting_table":2,"afeibailismod:cerulean_shove":14,"afeibailismod:cerulean_hoe":3,"afeibailismod:cerulean_axe":5,"afeibailismod:inferno_dragon":4,"minecraft:cobbled_deepslate":1},"minecraft:custom":{"minecraft:time_since_rest":3565,"minecraft:sprint_one_cm":10903,"minecraft:walk_one_cm":12293,"minecraft:drop":1,"minecraft:fly_one_cm":7042,"minecraft:interact_with_crafting_table":1,"minecraft:crouch_one_cm":128,"minecraft:play_time":3565,"minecraft:sneak_time":38,"minecraft:jump":15,"minecraft:leave_game":1,"minecraft:time_since_death":3565,"minecraft:total_world_time":3620},"minecraft:dropped":{"afeibailismod:cerulean_sword":1},"minecraft:mined":{"afeibailismod:cerulean_planks":1,"afeibailismod:ruby_ore":2,"minecraft:crafting_table":2,"minecraft:grass_block":19,"afeibailismod:sapphire_ore":2,"afeibailismod:cerulean_leaves":12,"afeibailismod:cerulean_log":4,"minecraft:deepslate":1}},"DataVersion":3337}